spectrally_regularised_lvms/__init__.py
spectrally_regularised_lvms/cost_functions.py
spectrally_regularised_lvms/helper_methods.py
spectrally_regularised_lvms/negen_approx.py
spectrally_regularised_lvms/spectral_regulariser.py
spectrally_regularised_lvms/spectrally_regularised_model.py
spectrally_regularised_lvms-0.1.4.dist-info/LICENSE
spectrally_regularised_lvms-0.1.4.dist-info/METADATA
spectrally_regularised_lvms-0.1.4.dist-info/WHEEL
spectrally_regularised_lvms-0.1.4.dist-info/RECORD
