Metadata-Version: 2.3
Name: spectrally-regularised-LVMs
Version: 0.1.4
Summary: A framework of linear LVMs with spectral regularisation.
License: MIT
Keywords: Linear LVMs,Spectral regularisation,Python
Author: Ryan Balshaw
Author-email: ryanbalshaw81@gmail.com
Maintainer: Ryan Balshaw
Maintainer-email: ryanbalshaw81@gmail.com
Requires-Python: >=3.11,<4.0
Classifier: Development Status :: 4 - Beta
Classifier: License :: OSI Approved :: MIT License
Classifier: Programming Language :: Python :: 3
Classifier: Programming Language :: Python :: Implementation
Classifier: Topic :: Scientific/Engineering
Requires-Dist: matplotlib (>=3.5.2)
Requires-Dist: numpy (>=1.23.1,<2.0)
Requires-Dist: scikit-learn (>=1.1.2)
Requires-Dist: scipy (>=1.8.1)
Requires-Dist: sympy (>=1.11.1,<1.13)
Requires-Dist: tqdm (>=4.64.1)
Project-URL: Bug tracker, https://github.com/RyanBalshaw/spectrally-regularised-LVMs/issues
